kodo/ast_generator.py
kodo/context_manager.py
kodo/main.py
kodo/agent/__init__.py
kodo/agent/core.py
kodo/config/settings.py
kodo/file_ops/__init__.py
kodo/file_ops/reader.py
kodo/file_ops/writer.py
kodo/llm/__init__.py
kodo/llm/providers.py
kodo_cli-0.1.0.dist-info/METADATA
kodo_cli-0.1.0.dist-info/WHEEL
kodo_cli-0.1.0.dist-info/entry_points.txt
kodo_cli-0.1.0.dist-info/RECORD
