Metadata-Version: 2.4
Name: kodo-cli
Version: 0.1.0
Summary: Kodo - A simple cli agent
Author: Angkul
Requires-Python: >=3.8
Requires-Dist: litellm
Requires-Dist: python-dotenv
Requires-Dist: rich
Requires-Dist: tree-sitter
Requires-Dist: tree-sitter-language-pack
Requires-Dist: typer[all]
